nyx/cli.py
nyx/exceptions.py
nyx/main.py
nyx/model.py
pynyx-0.0.10.dist-info/METADATA
pynyx-0.0.10.dist-info/WHEEL
pynyx-0.0.10.dist-info/entry_points.txt
pynyx-0.0.10.dist-info/RECORD
