Metadata-Version: 2.1
Name: pyNyx
Version: 0.0.10
Summary: nyx rules processing and conversion tools
License: MIT
Author: arblade
Author-email: raphael.arblade@gmail.com
Requires-Python: >=3.10,<4.0
Classifier: License :: OSI Approved :: MIT License
Classifier: Programming Language :: Python :: 3
Classifier: Programming Language :: Python :: 3.10
Classifier: Programming Language :: Python :: 3.11
Classifier: Programming Language :: Python :: 3.12
Requires-Dist: pyyaml (>=6.0.1,<7.0.0)
